autoanki/AutoAnki.py
autoanki/__init__.py
autoanki/BookCleaner/BookCleaner.py
autoanki/BookCleaner/__init__.py
autoanki/DatabaseManager/ChineseDatabaseManager.py
autoanki/DatabaseManager/DatabaseManager.py
autoanki/DatabaseManager/__init__.py
autoanki/DatabaseManager/book_table.sql
autoanki/DatabaseManager/book_table_view.sql
autoanki/DatabaseManager/databases_init.sql
autoanki/DeckManager/DeckManager.py
autoanki/DeckManager/__init__.py
autoanki/DeckManager/template_decks.py
autoanki/Dictionary/.DS_Store
autoanki/Dictionary/CEDictionary.py
autoanki/Dictionary/Dictionary.py
autoanki/Dictionary/__init__.py
autoanki/Dictionary/cedict_ts.u8
autoanki/Tokenizer/ChineseTokenizer.py
autoanki/Tokenizer/Tokenizer.py
autoanki/Tokenizer/__init__.py
autoanki-1.2.2.dist-info/LICENSE.txt
autoanki-1.2.2.dist-info/METADATA
autoanki-1.2.2.dist-info/WHEEL
autoanki-1.2.2.dist-info/top_level.txt
autoanki-1.2.2.dist-info/RECORD
