Metadata-Version: 2.1
Name: autoanki
Version: 1.2.2
Summary: Automatically make Anki Decks for Chinese text
Home-page: https://github.com/timmy6figures/autoanki
Author: Jarvis Coghlin
Author-email: jarviscoghlin@gmail.com
Project-URL: Bug Tracker, https://github.com/timmy6figures/autoanki/issues
Classifier: Programming Language :: Python :: 3
Classifier: License :: OSI Approved :: MIT License
Classifier: Operating System :: OS Independent
Requires-Python: >=3.10
License-File: LICENSE.txt
Requires-Dist: chinese-converter >=1.1.1
Requires-Dist: beautifulsoup4 ~=4.12.2
Requires-Dist: ebooklib
Requires-Dist: genanki ~=0.13.0
Requires-Dist: jieba ~=0.42.1
Requires-Dist: pandas
Requires-Dist: pdfplumber ~=0.11.0
Requires-Dist: pinyin ~=0.4.0
Requires-Dist: pydub
Requires-Dist: requests ~=2.31.0
Requires-Dist: wordfreq
